[
    {
        "id": 1,
        "name": "Laura Palmer",
        "image": "https://images.wikia.nocookie.net/__cb20180219220542/twinpeaks/images/thumb/9/92/Laura_Palmer_%281989%29.jpg/130px-0%2C1024%2C14%2C920-Laura_Palmer_%281989%29.jpg"
    },
    {
        "id": 2,
        "name": "Dale Cooper",
        "image": "https://images.wikia.nocookie.net/__cb20160916044627/twinpeaks/images/thumb/8/82/CooperSelfPortrait.png/130px-0%2C138%2C3%2C125-CooperSelfPortrait.png"
    },
    {
        "id": 3,
        "name": "Audrey Horne",
        "image": "https://images.wikia.nocookie.net/__cb20170731215823/twinpeaks/images/thumb/7/79/AudreyHorne2014.jpg/130px-0%2C417%2C7%2C376-AudreyHorne2014.jpg"
    },
    {
        "id": 4,
        "name": "Bob",
        "image": "https://images.wikia.nocookie.net/__cb20100423043335/twinpeaks/images/thumb/3/37/KillerBob.jpg/130px-0%2C1746%2C34%2C1579-KillerBob.jpg"
    },
    {
        "id": 5,
        "name": "Harry S. Truman",
        "image": "https://images.wikia.nocookie.net/__cb20161026022237/twinpeaks/images/thumb/c/c7/HarryNew.jpg/130px-0%2C1003%2C13%2C900-HarryNew.jpg"
    },
    {
        "id": 6,
        "name": "Leland Palmer",
        "image": "https://images.wikia.nocookie.net/__cb20170625011021/twinpeaks/images/thumb/d/df/Leland2017.png/130px-0%2C378%2C5%2C339-Leland2017.png"
    },
    {
        "id": 7,
        "name": "Donna Hayward",
        "image": "https://images.wikia.nocookie.net/__cb20100419235618/twinpeaks/images/thumb/0/0c/Donna_001.jpg/130px-0%2C1115%2C21%2C1007-Donna_001.jpg"
    },
    {
        "id": 8,
        "name": "Sarah Palmer",
        "image": "https://images.wikia.nocookie.net/__cb20170731011136/twinpeaks/images/thumb/f/fa/Sarah_palmer_2017.png/130px-0%2C671%2C10%2C604-Sarah_palmer_2017.png"
    },
    {
        "id": 9,
        "name": "James Hurley",
        "image": "https://images.wikia.nocookie.net/__cb20170807173150/twinpeaks/images/thumb/9/90/JamesRoadhouse.png/130px-0%2C356%2C6%2C321-JamesRoadhouse.png"
    },
    {
        "id": 10,
        "name": "Giant",
        "image": "https://images.wikia.nocookie.net/__cb20161014151543/twinpeaks/images/thumb/b/b4/GiantNew.png/130px-45%2C538%2C0%2C435-GiantNew.png"
    },
    {
        "id": 11,
        "name": "Shelly Johnson",
        "image": "https://images.wikia.nocookie.net/__cb20180112042048/twinpeaks/images/thumb/4/47/Shelly_Briggs_%282010s%29.jpg/130px-0%2C592%2C9%2C533-Shelly_Briggs_%282010s%29.jpg"
    },
    {
        "id": 12,
        "name": "Pete Martell",
        "image": "https://images.wikia.nocookie.net/__cb20170822052012/twinpeaks/images/thumb/3/3d/Pete_Martell.jpg/130px-0%2C625%2C10%2C563-Pete_Martell.jpg"
    }
]